{
    "main": [
        {
            "title": " ",
            "type": "home",
            "link": "/",
            "public": true
        },
        {
            "title": " ",
            "type": "about",
            "link": "/about",
            "anim": true,
            "public": true
        },
        {
            "title": " ",
            "type": "info",
            "link": "/info",
            "anim": true,
            "public": true
        },
        {
            "title": " ",
            "type": "contact",
            "link": "/contact",
            "anim": true,
            "public": true
        }
    ]
}
